snowglobe/telemetry/mlflow/__init__.py
snowglobe/telemetry/mlflow/mlflow_instrumentor.py
snowglobe_telemetry_mlflow-0.0.2.dist-info/licenses/LICENSE
snowglobe_telemetry_mlflow-0.0.2.dist-info/METADATA
snowglobe_telemetry_mlflow-0.0.2.dist-info/WHEEL
snowglobe_telemetry_mlflow-0.0.2.dist-info/top_level.txt
snowglobe_telemetry_mlflow-0.0.2.dist-info/RECORD
